MSSQL/__init__.py
MSSQL/__main__.py
MSSQL/test_connection.py
MSSQL/test_cursor.py
MSSQL/test_execute.py
MSSQL/test_row.py
MSSQL/test_types.py
tkinter_mssql-0.2.3.dist-info/licenses/LICENSE
tkinter_mssql-0.2.3.dist-info/METADATA
tkinter_mssql-0.2.3.dist-info/WHEEL
tkinter_mssql-0.2.3.dist-info/entry_points.txt
tkinter_mssql-0.2.3.dist-info/top_level.txt
tkinter_mssql-0.2.3.dist-info/RECORD
