Metadata-Version: 2.4
Name: Tkinter-MSSQL
Version: 0.2.3
Summary: Приложение для управления заявками и партнерами на базе Microsoft SQL Server
Author: John Doe
Author-email: thenonnss45@gmail.com
Classifier: Programming Language :: Python :: 3
Classifier: License :: OSI Approved :: MIT License
Classifier: Operating System :: OS Independent
Requires-Python: >=3.7
License-File: LICENSE
Requires-Dist: pyodbc
Requires-Dist: pillow
Dynamic: author
Dynamic: author-email
Dynamic: classifier
Dynamic: license-file
Dynamic: requires-dist
Dynamic: requires-python
Dynamic: summary
